xtip/__init__.py
xtip/__main__.py
xtip/commands.py
xtip/xtip.py
xtip-0.2.0.dist-info/entry_points.txt
xtip-0.2.0.dist-info/WHEEL
xtip-0.2.0.dist-info/METADATA
xtip-0.2.0.dist-info/RECORD
