Metadata-Version: 2.1
Name: xtip
Version: 0.2.0
Summary: Run commands on selected text quickly
Home-page: https://github.com/davidshepherd7/xtip
License: MIT
Author: David Shepherd
Author-email: davidshepherd7@gmail.com
Requires-Python: >=3.6,<4.0
Classifier: License :: OSI Approved :: MIT License
Classifier: Programming Language :: Python :: 3
Classifier: Programming Language :: Python :: 3.6
Classifier: Programming Language :: Python :: 3.7
Classifier: Programming Language :: Python :: 3.8
Provides-Extra: google-translate
